Metadata-Version: 1.0
Name: stat-distribution-curves
Version: 0.1
Summary: Gaussian Distribution
Home-page: UNKNOWN
Author: UNKNOWN
Author-email: UNKNOWN
License: UNKNOWN
Platform: UNKNOWN
